brew_virustotal/__init__.py
brew_virustotal/cli.py
brew_virustotal-0.1.4.dist-info/entry_points.txt
brew_virustotal-0.1.4.dist-info/LICENSE
brew_virustotal-0.1.4.dist-info/WHEEL
brew_virustotal-0.1.4.dist-info/METADATA
brew_virustotal-0.1.4.dist-info/RECORD
