Metadata-Version: 2.1
Name: brew-virustotal
Version: 0.1.4
Summary: Check Homebrew formulae and casks with VirusTotal
Home-page: https://github.com/tddschn/brew-virustotal
License: MIT
Keywords: homebrew,virustotal
Author: Xinyuan Chen
Author-email: 45612704+tddschn@users.noreply.github.com
Requires-Python: >=3.10,<4.0
Classifier: License :: OSI Approved :: MIT License
Classifier: Programming Language :: Python :: 3
Classifier: Programming Language :: Python :: 3.10
Classifier: Topic :: Utilities
Requires-Dist: virustotal-tddschn (>=0.1.6,<0.2.0)
Project-URL: Bug Tracker, https://github.com/tddschn/brew-virustotal/issues
Project-URL: Repository, https://github.com/tddschn/brew-virustotal
